{
    "FECHA": "2026-03-26 18:18:21",
    "HTTP_REQUEST_TRACE": {
        "method": "GET",
        "url": "https:\/\/000357-017.connect.axoft.com\/Api\/Api\/Get?process=2941&pageSize=100&pageIndex=0&view=",
        "headers": [
            "ApiAuthorization: 390A44F6-EE7C-4AFB-80CC-227CBA68FFC3",
            "Company: 157",
            "Accept: application\/json",
            "Content-Type: application\/json",
            "Client-Id: 000357\/017"
        ]
    },
    "LISTAS_API_RAW": {
        "status": 200,
        "data": null
    },
    "DEPOSITOS_API_RAW": {
        "status": 200,
        "data": null
    },
    "LISTAS_NORMALIZADAS": [],
    "DEPOSITOS_NORMALIZADOS": [],
    "VALOR_DB": {
        "lista_default": "",
        "lista_alternate": "",
        "deposito_codigo": ""
    }
}